{
  "run_id": "20251114T104916Z",
  "generated_at": "2025-11-14T10:49:17.045019Z",
  "context_hash": "5f59aef27fa5598ce0b30c080d89966420ab9892c0ea9f19c30f18021863383b",
  "model": "llama3.1:8b",
  "sections": [
    {
      "slug": "overview",
      "title": "Executive Overview",
      "content": "## Executive Overview\n\nRedacted Organisation is committed to upholding the highest standards of data protection and privacy. As a responsible entity, we acknowledge our role in processing personal data and strive to ensure that all activities are conducted in accordance with the principles of transparency, accountability, and respect for individual rights.\n\nOur organisation processes personal data on a limited scale, primarily for purposes related to [Information available on request]. We do not have an established website, but our contact details are as follows: Email: asfaf. Our Data Protection Officer (DPO) is also available at this email address. For more information regarding our establishment country, please note that it has not been specified.\n\nWe take pride in our commitment to data protection and aim to maintain a strong risk posture of 94% (rating: Strong). We are dedicated to ensuring the lawfulness, transparency, and accountability of our processing activities, while also prioritising privacy-by-design principles. Our goal is to provide a secure environment for individuals whose personal data we process.\n\n### Key Objectives\n\n* To ensure that all processing activities are lawful, fair, and transparent, with clear purposes and procedures in place.\n* To maintain open communication channels with stakeholders, providing accessible information about our data handling practices.\n* To be accountable for any data breaches or incidents, taking swift action to mitigate harm and restore trust.\n* To design and implement systems that respect individuals' rights to privacy, security, and control over their personal data.\n\nOur organisation is committed to aligning its policies and procedures with the requirements of both the General Data Protection Regulation (GDPR) and the UK GDPR. We aim to maintain a strong risk posture while continuously monitoring and improving our data protection practices."
    },
    {
      "slug": "data_processing",
      "title": "Data Processing & Registers",
      "content": "## Data Processing Activities\n\nOur organisation processes personal data for various purposes, primarily to comply with legal obligations and obtain consent from individuals. The processing register is currently empty, indicating that no records have been submitted for review at this time. However, we are committed to maintaining accurate and up-to-date records of our processing activities.\n\nIn terms of cookies, they are not enabled on our website due to the lack of an online presence. This decision was made in accordance with our organisation's policies and procedures. We do not engage any external processors for data processing at this time. However, we may consider engaging third-party vendors in the future if necessary, subject to thorough risk assessments and contractual agreements.\n\nWe retain personal data for a period of three months, which is based on our assessment of the relevant criteria, including the purposes for which the data was collected and the potential risks associated with its storage. This retention period aligns with our lawful bases, particularly consent, as individuals have the right to withdraw their consent at any time.\n\n### Processing Register\n\n\u2022 Records are being finalised.\n\n### Processors\n\nNo external processors declared at this time.\n\n### International Transfers and Safeguards\n\nTransfers of personal data outside the European Economic Area (EEA) are not currently recorded. However, we will update our policy to reflect any future transfers and ensure that adequate safeguards are in place, such as standard contractual clauses or binding corporate rules.\n\n### Retention\n\nWe retain personal data for a period of three months from the date of collection. This retention period is based on our assessment of the relevant criteria, including the purposes for which the data was collected and the potential risks associated with its storage. Our lawful bases, particularly consent, also inform this decision, as individuals have the right to withdraw their consent at any time.\n\nOur organisation's commitment to transparency and accountability in data processing activities is reflected in our GDPR policy, which will be regularly reviewed and updated to ensure compliance with relevant regulations and best practices."
    },
    {
      "slug": "lawful_bases",
      "title": "Lawful Bases & Transparency",
      "content": "## Lawful Bases and Transparency\n\nIn accordance with Article 5 of the General Data Protection Regulation (GDPR), which emphasizes the importance of lawfulness, fairness, transparency, and accountability in data processing, our organization has identified the lawful bases for processing personal data. As per Article 6, we have declared the following lawful bases: Consent and Legal Obligation.\n\nThe following lawful bases are declared:\n\n* **Consent**: Applied when an individual provides explicit consent to process their personal data.\n* **Legal Obligation**: Applied when processing is necessary to comply with a legal obligation under EU or Member State law.\n\nPlease note that if no lawful basis is declared, it will be documented prior to processing.\n\nIn addition to declaring the lawful bases, our organization also ensures transparency in its data processing activities. We provide privacy notices and cookie practices (although cookies are currently disabled) to inform individuals about how their personal data is collected, stored, and processed. Data subject information is supplied through our website, and we handle rights requests in accordance with Article 12 of the GDPR.\n\nAs cookies are currently disabled on our website, no cookie-related activities are taking place at this time. However, when cookies are enabled, we will provide clear information about their use and purposes. Our organization remains committed to transparency and accountability in all its data processing activities."
    },
    {
      "slug": "rights",
      "title": "Data Subject Rights",
      "content": "## Data Subject Rights\n\nAs a data subject, you have various rights under the General Data Protection Regulation (GDPR) that allow you to control how your personal data is processed. At Redacted Organisation, we respect and support these rights, ensuring transparency in our practices.\n\n### Core GDPR Rights\n\nWe enable the following core rights as per the GDPR:\n\n1. **Access**: You have the right to access your personal data held by us.\n2. **Rectification**: If you believe any of your personal data is inaccurate or incomplete, we will rectify it upon request.\n3. **Erasure**: In certain circumstances, you may request erasure of your personal data from our records.\n4. **Restriction**: You can restrict the processing of your personal data in specific situations.\n5. **Portability**: We facilitate the transfer of your personal data to another controller where technically feasible.\n6. **Objection**: You have the right to object to the processing of your personal data for direct marketing purposes or other legitimate interests.\n7. **Automated Decisions**: If we make decisions based on automated processes, you can request information about these processes and their logic.\n\n### Additional Rights\n\nWe also support additional rights as per our organisational policies:\n\n1. **Right to Data Portability**: We facilitate the transfer of your personal data to another controller where technically feasible.\n2. **Right to Object**: You have the right to object to the processing of your personal data for direct marketing purposes or other legitimate interests.\n\n### Submitting Requests\n\nIf you wish to exercise any of these rights, please follow this procedure:\n\n1. Write to us at: Email: [asfaf](mailto:asfaf)\n2. Clearly state which right(s) you wish to invoke and provide details about the specific data in question.\n3. We will acknowledge your request within 24 hours and respond with a decision within one month of receipt, unless the complexity of the request requires additional time.\n\n### Response Timelines and Verification\n\nWe strive to process all requests as quickly as possible while ensuring accuracy and thoroughness. In some cases, we may need more time to verify information or consult with other departments. We will inform you in advance if this is necessary and provide an estimated timeline for completion.\n\nUpon receiving your request, we will verify the identity of the data subject to ensure that only authorized individuals can access or modify their personal data. This verification process may involve asking additional questions or requesting documentation to confirm your identity.\n\n### Contact Instructions\n\nIf you have any questions about our Data Subject Rights policy or wish to submit a request, please contact our DPO via the published privacy email at [asfaf](mailto:asfaf). If you need more information on how to proceed with your request, please do not hesitate to reach out."
    },
    {
      "slug": "security",
      "title": "Security & Incident Response",
      "content": "## Security and Incident Response\n\n### Preventive and Detective Controls\n\nTo ensure the security of personal data, we have implemented various preventive and detective controls. These measures are designed to prevent unauthorized access or breaches, as well as detect any potential incidents in a timely manner.\n\nPreventive controls include [insert placeholder for ctx[\"security_measures\"]], which will be reviewed and updated regularly to ensure they remain effective. Additionally, our organization has established clear policies and procedures for data handling, storage, and transmission, including the use of encryption and secure protocols for data transfer. These measures are designed to minimize the risk of a breach occurring in the first place.\n\nDetective controls include [insert placeholder for ctx[\"security_measures\"]], which will be monitored regularly to detect any potential security incidents. Our organization also has in place incident response procedures, including notification requirements under Articles 33 and 34 of the GDPR. These procedures ensure that any breaches are reported promptly and effectively to the relevant authorities and stakeholders.\n\n### Breach Response Timeline\n\nIn the event of a breach, our organization will follow a clear and structured timeline for response and notification. This includes:\n\n* Immediate containment of the breach to prevent further damage\n* Notification to the relevant authorities, including the Data Protection Authority (DPA) and any affected individuals or processors/transfers under Article 33(1)\n* Investigation into the cause and extent of the breach, with a view to implementing corrective measures to prevent similar incidents in the future\n* Communication with affected stakeholders, including processors/transfers, under Article 34\n\n### Key Controls\n\nThe following key controls are in place to ensure the security and integrity of personal data:\n\n\u2022 Cookies are disabled on our website due to its absence.\n\u2022 We rely on lawful bases of Consent and Legal Obligation for processing personal data.\n\u2022 Personal data is retained for a maximum period of 3 months.\n\u2022 Our organization has a risk rating of Strong, with a risk score of 94.0%.\n\u2022 We have established clear policies and procedures for data handling, storage, and transmission.\n\u2022 Regular monitoring and review of security measures are in place to ensure their effectiveness.\n\nNote: The placeholder text is used as the ctx[\"security_measures\"] field is empty."
    },
    {
      "slug": "governance",
      "title": "Governance & Contacts",
      "content": "## Governance, Roles, and Contacts\n\nOur organization is committed to ensuring that our processing of personal data is carried out in accordance with the principles of transparency, accountability, and respect for individuals' rights. As part of this commitment, we have established a governance framework that outlines the roles and responsibilities of various stakeholders within our organization.\n\n### Accountability Model\n\nAt the heart of our accountability model is the Data Protection Officer (DPO), who serves as the primary point of contact for all data protection-related matters. The DPO is responsible for ensuring that our organization complies with the General Data Protection Regulation (GDPR) and other relevant data protection laws. The DPO's role includes conducting regular risk assessments, implementing measures to mitigate identified risks, and providing guidance to senior leadership on data protection matters.\n\nOur organization recognizes that we operate in a global context, and as such, we have established a governance framework that takes into account the sector and country-specific requirements for data protection. While our establishment country is not specified, we are committed to ensuring that our processing of personal data complies with the relevant laws and regulations applicable to our operations.\n\n### Roles and Responsibilities\n\nThe following roles and responsibilities have been established within our organization:\n\n* **Senior Leadership**: Senior leadership is responsible for ensuring that data protection is integrated into all business activities and decisions. They must ensure that adequate resources are allocated to support the implementation of data protection measures.\n* **Processors**: Processors, including third-party vendors and contractors, are responsible for ensuring that they comply with our organization's data protection policies and procedures. They must also ensure that their own processing activities comply with relevant laws and regulations.\n* **Data Protection Teams**: Data protection teams, led by the DPO, are responsible for implementing and maintaining our organization's data protection policies and procedures. They must conduct regular risk assessments, implement measures to mitigate identified risks, and provide guidance to senior leadership on data protection matters.\n* **Oversight Bodies**: Oversight bodies, including regulatory authorities and industry associations, play a critical role in ensuring that our organization complies with relevant laws and regulations.\n\n### Contact Instructions\n\nIf you have any questions or concerns about our data protection policies and procedures, please contact us at:\n\nEmail: [asfaf](mailto:asfaf)\n\nPlease note that while we strive to provide accurate and up-to-date information on this page, there may be instances where data is missing or incomplete. In such cases, please do not hesitate to contact us directly for further assistance.\n\nWe are committed to ensuring that our organization complies with the GDPR and other relevant data protection laws. If you have any concerns about our compliance, please do not hesitate to contact us at the above email address."
    }
  ],
  "policy_number": "GDP-20251114T104916Z",
  "signature": "2b1d34fba1f43f55c1520574883856a5e6a83891afd7929a0d54cf2bae5b803b",
  "paths": {
    "markdown": "output/official/20251114T104916Z/policy.md",
    "html": "output/official/20251114T104916Z/policy.html",
    "pdf": "output/official/20251114T104916Z/policy.pdf"
  }
}